streamlit_cropper/__init__.py
streamlit_cropper/frontend/.prettierrc
streamlit_cropper/frontend/package-lock.json
streamlit_cropper/frontend/package.json
streamlit_cropper/frontend/tsconfig.json
streamlit_cropper/frontend/public/bootstrap.min.css
streamlit_cropper/frontend/public/index.html
streamlit_cropper/frontend/src/.env
streamlit_cropper/frontend/src/StreamlitCropper.tsx
streamlit_cropper/frontend/src/index.css
streamlit_cropper/frontend/src/index.tsx
streamlit_cropper/frontend/src/react-app-env.d.ts
streamlit_cropper/frontend/src/streamlit/StreamlitReact.tsx
streamlit_cropper/frontend/src/streamlit/index.tsx
streamlit_cropper/frontend/src/streamlit/streamlit.ts
streamlit_cropper-0.3.0.dist-info/METADATA
streamlit_cropper-0.3.0.dist-info/WHEEL
streamlit_cropper-0.3.0.dist-info/licenses/LICENSE
streamlit_cropper-0.3.0.dist-info/RECORD
