Metadata-Version: 2.4
Name: streamlit-cropper
Version: 0.3.0
Summary: A simple image cropper for Streamlit
Project-URL: Homepage, https://github.com/turner-anderson/streamlit-cropper
Project-URL: Bug Tracker, https://github.com/turner-anderson/streamlit-cropper/issues
Author-email: Turner Anderson <andersontur11@gmail.com>
License-File: LICENSE
Classifier: License :: OSI Approved :: MIT License
Classifier: Operating System :: OS Independent
Classifier: Programming Language :: Python :: 3
Requires-Python: >=3.10
Requires-Dist: numpy
Requires-Dist: pillow
Requires-Dist: streamlit
